jdc/__init__.py
jdc/__version__.py
jdc-0.0.9.dist-info/METADATA
jdc-0.0.9.dist-info/WHEEL
jdc-0.0.9.dist-info/top_level.txt
jdc-0.0.9.dist-info/RECORD
